{
  "title": "测试项目笔记",
  "categories": [
    {
      "name": "默认分类1",
      "subcategories": [
        {
          "name": "默认子分类1"
        },
        {
          "name": "默认子分类2"
        },
        {
          "name": "默认子分类3"
        },
        {
          "name": "默认子分类4"
        }
      ]
    },
    {
      "name": "默认分类2",
      "subcategories": [
        {
          "name": "默认子分类1"
        },
        {
          "name": "默认子分类2"
        },
        {
          "name": "默认子分类3"
        },
        {
          "name": "默认子分类4"
        }
      ]
    },
    {
      "name": "默认分类3",
      "subcategories": [
        {
          "name": "默认子分类1"
        },
        {
          "name": "默认子分类2"
        },
        {
          "name": "默认子分类3"
        },
        {
          "name": "默认子分类4"
        }
      ]
    },
    {
      "name": "默认分类4",
      "subcategories": [
        {
          "name": "默认子分类1"
        },
        {
          "name": "默认子分类2"
        },
        {
          "name": "默认子分类3"
        },
        {
          "name": "默认子分类4"
        }
      ]
    }
  ]
}